sxPDK/__init__.py
sxPDK/pluginDevelopment.py
sxPDK-1.5.4.dist-info/LICENSE.txt
sxPDK-1.5.4.dist-info/METADATA
sxPDK-1.5.4.dist-info/WHEEL
sxPDK-1.5.4.dist-info/top_level.txt
sxPDK-1.5.4.dist-info/RECORD
