Metadata-Version: 2.1
Name: sxPDK
Version: 1.5.4
Summary: The Plugin Development Kit for ShieldX Manager.
Home-page: https://github.com/Lemon-Chad/sxPDK
Author: LemonChad
Author-email: jakitmationstudios@gmail.com
License: MIT
Download-URL: https://github.com/Lemon-Chad/sxPDK/archive/v_1.5.4.zip
Keywords: discord.py,shieldx,shieldxplugins
Platform: UNKNOWN
Classifier: Development Status :: 5 - Production/Stable
Classifier: Intended Audience :: Developers
Classifier: Topic :: Software Development :: Build Tools
Classifier: License :: OSI Approved :: MIT License
Classifier: Programming Language :: Python :: 3
Classifier: Programming Language :: Python :: 3.4
Classifier: Programming Language :: Python :: 3.5
Classifier: Programming Language :: Python :: 3.6
Requires-Dist: discord
